paper_rq/__init__.py
paper_rq/admin.py
paper_rq/apps.py
paper_rq/decorators.py
paper_rq/exceptions.py
paper_rq/helpers.py
paper_rq/jobs.py
paper_rq/list_queryset.py
paper_rq/models.py
paper_rq/patches.py
paper_rq/scheduler.py
paper_rq/migrations/0001_initial.py
paper_rq/migrations/0002_resultmodel.py
paper_rq/migrations/__init__.py
paper_rq/static/paper_rq/invalid.svg
paper_rq/templates/paper_rq/job_changeform.html
paper_rq/templates/paper_rq/job_changelist_tools.html
paper_rq/templates/paper_rq/job_results.html
paper_rq/templates/paper_rq/queue_changeform.html
paper_rq/templates/paper_rq/queue_changelist_tools.html
paper_rq/templates/paper_rq/worker_changeform.html
paper_rq-0.8.5.dist-info/LICENSE
paper_rq-0.8.5.dist-info/METADATA
paper_rq-0.8.5.dist-info/WHEEL
paper_rq-0.8.5.dist-info/top_level.txt
paper_rq-0.8.5.dist-info/RECORD
