Metadata-Version: 2.1
Name: paper-rq
Version: 0.8.5
Summary: An administrative interface for managing RQ tasks in Paper Admin
Home-page: https://github.com/dldevinc/paper-rq
Author: Mihail Mishakin
Author-email: x896321475@gmail.com
Maintainer: Mihail Mishakin
Maintainer-email: x896321475@gmail.com
License: BSD license
Platform: OS Independent
Classifier: Intended Audience :: Developers
Classifier: Development Status :: 3 - Alpha
Classifier: License :: OSI Approved :: BSD License
Classifier: Operating System :: OS Independent
Classifier: Framework :: Django :: 3.2
Classifier: Framework :: Django :: 4.0
Classifier: Framework :: Django :: 4.1
Classifier: Framework :: Django :: 4.2
Classifier: Programming Language :: Python
Classifier: Programming Language :: Python :: 3
Classifier: Programming Language :: Python :: 3 :: Only
Classifier: Programming Language :: Python :: 3.7
Classifier: Programming Language :: Python :: 3.8
Classifier: Programming Language :: Python :: 3.9
Classifier: Programming Language :: Python :: 3.10
Classifier: Programming Language :: Python :: 3.11
Classifier: Topic :: Software Development :: Libraries :: Python Modules
Requires-Python: >=3.7
License-File: LICENSE
Requires-Dist: django>=3.2
Requires-Dist: paper-admin>=6.0
Requires-Dist: django-rq>=2.4
Requires-Dist: rq>=1.11
